allure_pytest_default_results/__init__.py
allure_pytest_default_results/_plugin.py
allure_pytest_default_results-0.1.3.dist-info/METADATA
allure_pytest_default_results-0.1.3.dist-info/WHEEL
allure_pytest_default_results-0.1.3.dist-info/entry_points.txt
allure_pytest_default_results-0.1.3.dist-info/RECORD
