Metadata-Version: 2.1
Name: allure-pytest-default-results
Version: 0.1.3
Summary: Generate default "unknown" results to show in Allure Report if test case does not run
Author: Carl Csaposs
Author-email: carl.csaposs@canonical.com
Requires-Python: >=3.8
Classifier: Framework :: Pytest
Classifier: Programming Language :: Python :: 3
Classifier: Programming Language :: Python :: 3.8
Classifier: Programming Language :: Python :: 3.9
Classifier: Programming Language :: Python :: 3.10
Classifier: Programming Language :: Python :: 3.11
Classifier: Programming Language :: Python :: 3.12
Classifier: Programming Language :: Python :: 3.13
Requires-Dist: allure-pytest (>=2.13.5)
Requires-Dist: pytest
Project-URL: repository, https://github.com/canonical/allure-pytest-default-results
